{"cameraMode":{"drawMode":0,"name":"Shaded","section":"Shading Mode"},"sceneLighting":true,"audioPlay":false,"sceneViewState":{"showFog":true,"showMaterialUpdate":false,"showSkybox":true,"showFlares":true,"showImageEffects":true,"showParticleSystems":true},"in2DMode":false,"pivot":{"x":184.85848999023438,"y":-252.6710205078125,"z":-451.21734619140627},"rotation":{"x":-0.04531082138419151,"y":-0.9540722370147705,"z":0.22862879931926728,"w":-0.18870416283607484},"size":566.7565307617188,"orthographic":false}